concrete/__init__.py
concrete/numpy/__init__.py
concrete/numpy/compilation/__init__.py
concrete/numpy/compilation/artifacts.py
concrete/numpy/compilation/circuit.py
concrete/numpy/compilation/client.py
concrete/numpy/compilation/compiler.py
concrete/numpy/compilation/configuration.py
concrete/numpy/compilation/decorators.py
concrete/numpy/compilation/server.py
concrete/numpy/compilation/specs.py
concrete/numpy/compilation/utils.py
concrete/numpy/dtypes/__init__.py
concrete/numpy/dtypes/base.py
concrete/numpy/dtypes/float.py
concrete/numpy/dtypes/integer.py
concrete/numpy/dtypes/utils.py
concrete/numpy/extensions/__init__.py
concrete/numpy/extensions/array.py
concrete/numpy/extensions/ones.py
concrete/numpy/extensions/round_bit_pattern.py
concrete/numpy/extensions/table.py
concrete/numpy/extensions/tag.py
concrete/numpy/extensions/univariate.py
concrete/numpy/extensions/zeros.py
concrete/numpy/internal/__init__.py
concrete/numpy/internal/utils.py
concrete/numpy/mlir/__init__.py
concrete/numpy/mlir/graph_converter.py
concrete/numpy/mlir/node_converter.py
concrete/numpy/mlir/utils.py
concrete/numpy/representation/__init__.py
concrete/numpy/representation/evaluator.py
concrete/numpy/representation/graph.py
concrete/numpy/representation/node.py
concrete/numpy/representation/operation.py
concrete/numpy/representation/utils.py
concrete/numpy/tracing/__init__.py
concrete/numpy/tracing/tracer.py
concrete/numpy/tracing/typing.py
concrete/numpy/values/__init__.py
concrete/numpy/values/scalar.py
concrete/numpy/values/tensor.py
concrete/numpy/values/value.py
concrete/onnx/__init__.py
concrete/onnx/convolution.py
concrete/onnx/maxpool.py
concrete_numpy-0.11.1.dist-info/LICENSE
concrete_numpy-0.11.1.dist-info/METADATA
concrete_numpy-0.11.1.dist-info/WHEEL
concrete_numpy-0.11.1.dist-info/RECORD
