Metadata-Version: 2.1
Name: concrete-numpy
Version: 0.11.1
Summary: Concrete Numpy is an open-source library which simplifies the use of fully homomorphic encryption (FHE).
Home-page: https://zama.ai/concrete/
License: BSD-3-Clause
Keywords: FHE,homomorphic encryption,privacy,security
Author: Zama
Author-email: hello@zama.ai
Requires-Python: >=3.7,<3.12
Classifier: License :: OSI Approved :: BSD License
Classifier: Programming Language :: Python :: 3
Classifier: Programming Language :: Python :: 3.7
Classifier: Programming Language :: Python :: 3.8
Classifier: Programming Language :: Python :: 3.9
Classifier: Programming Language :: Python :: 3.10
Classifier: Programming Language :: Python :: 3.11
Classifier: Topic :: Scientific/Engineering
Classifier: Topic :: Scientific/Engineering :: Artificial Intelligence
Classifier: Topic :: Scientific/Engineering :: Mathematics
Classifier: Topic :: Security
Classifier: Topic :: Security :: Cryptography
Classifier: Topic :: Software Development :: Compilers
Requires-Dist: concrete-compiler (==0.24.0rc5)
Requires-Dist: matplotlib (>=3.5.1,<4.0.0)
Requires-Dist: networkx (>=2.6.3,<3.0.0)
Requires-Dist: numpy (==1.21.6) ; python_full_version < "3.8.0"
Requires-Dist: numpy (>=1.23.5,<2.0.0) ; python_full_version >= "3.8.0"
Requires-Dist: scipy (==1.7.3) ; python_full_version < "3.8.0"
Requires-Dist: scipy (>=1.10.1,<2.0.0) ; python_full_version >= "3.8.0"
Requires-Dist: torch (>=1.13.1,<2.0.0)
Project-URL: Bug Tracker, https://github.com/zama-ai/concrete-numpy/issues
Project-URL: Documentation, http://docs.zama.ai/concrete-numpy/
Project-URL: Discourse, https://community.zama.ai/c/concrete-numpy/7
Project-URL: Repository, https://github.com/zama-ai/concrete-numpy
Project-URL: README, https://github.com/zama-ai/concrete-numpy/blob/main/README.md
